```python
def foo(a, b=1, /, c=2, *args, d, **kwargs):
    print(a)
    print(b)
    print(c)
    print(args)
    print(d)
    print(kwargs)
    local_var1 = 100
    local_var2 = 200
    print(local_var1)
    print(local_var2)


# python inspect 模块中讲述
# *************************************************************************
print(foo.__code__.co_name)  # output为 foo
print(foo.__code__.co_code)  # output为 string
# >>> dis.dis(foo)
#   2           0 LOAD_GLOBAL              0 (print)
#               2 LOAD_FAST                0 (a)
#               4 CALL_FUNCTION            1
#               6 POP_TOP
#   3           8 LOAD_GLOBAL              0 (print)
#              10 LOAD_FAST                1 (b)
#              12 CALL_FUNCTION            1
#              14 POP_TOP
#   4          16 LOAD_GLOBAL              0 (print)
#              18 LOAD_FAST                2 (c)
#              20 CALL_FUNCTION            1
#              22 POP_TOP
#   5          24 LOAD_GLOBAL              0 (print)
#              26 LOAD_FAST                4 (args)
#              28 CALL_FUNCTION            1
#              30 POP_TOP
#   6          32 LOAD_GLOBAL              0 (print)
#              34 LOAD_FAST                3 (d)
#              36 CALL_FUNCTION            1
#              38 POP_TOP
#   7          40 LOAD_GLOBAL              0 (print)
#              42 LOAD_FAST                5 (kwargs)
#              44 CALL_FUNCTION            1
#              46 POP_TOP
#   8          48 LOAD_CONST               1 (100)
#              50 STORE_FAST               6 (local_var1)
#   9          52 LOAD_CONST               2 (200)
#              54 STORE_FAST               7 (local_var2)
#  10          56 LOAD_GLOBAL              0 (print)
#              58 LOAD_FAST                6 (local_var1)
#              60 CALL_FUNCTION            1
#              62 POP_TOP
#  11          64 LOAD_GLOBAL              0 (print)
#              66 LOAD_FAST                7 (local_var2)
#              68 CALL_FUNCTION            1
#              70 POP_TOP
#              72 LOAD_CONST               0 (None)
#              74 RETURN_VALUE


# *************************************************************************

# co_argcount: number of arguments (not including keyword only arguments, * or ** args)
print(foo.__code__.co_argcount)  # output为3， 代表参数a、参数b、参数c

# co_posonlyargcount: number of positional only arguments
print(foo.__code__.co_posonlyargcount)  # output为2， 代表参数a、参数b

# co_kwonlyargcount: number of keyword only arguments (not including ** arg)
print(foo.__code__.co_kwonlyargcount)  # output为2， 代表参数d

# *************************************************************************

print(foo.__code__.co_names)  # output为 ('print',)
print(foo.__code__.co_consts)  # output为 (None, 100, 200)
print(foo.__code__.co_nlocals)  # output为 8, 代表有8个局部变量
print(foo.__code__.co_varnames)  # output为 ('a', 'b', 'c', 'd', 'args', 'kwargs', 'local_var1', 'local_var2')

```